libprogress/__init__.py
libprogress-3.0.2.post1.dist-info/LICENSE
libprogress-3.0.2.post1.dist-info/METADATA
libprogress-3.0.2.post1.dist-info/WHEEL
libprogress-3.0.2.post1.dist-info/top_level.txt
libprogress-3.0.2.post1.dist-info/RECORD
