Metadata-Version: 2.1
Name: libprogress
Version: 3.0.2.post1
Summary: Library containing progress bar generator
Home-page: https://git.bbaovanc.com/bbaovanc/libprogress
Author: BBaoVanC
Author-email: pypi@bbaovanc.com
License: UNKNOWN
Platform: UNKNOWN
Classifier: Programming Language :: Python :: 3
Classifier: License :: OSI Approved :: GNU General Public License v3 (GPLv3)
Classifier: Operating System :: OS Independent
Requires-Python: >=3.7
License-File: LICENSE
